<?xml version="1.0" encoding="utf-8"?>
<!DOCTYPE TS>
<TS version="2.1" language="en_US">
<!--
    English Translation File
-->

<!-- ========== Settings Navigation ========== -->
<context>
    <name>SettingsDialog</name>
    <message>
        <source>Shortcuts</source>
        <translation>Shortcuts</translation>
    </message>
    <message>
        <source>Long Screenshot</source>
        <translation>Long Screenshot</translation>
    </message>
    <message>
        <source>Smart Selection</source>
        <translation>Smart Selection</translation>
    </message>
    <message>
        <source>Save Settings</source>
        <translation>Save Settings</translation>
    </message>
    <message>
        <source>OCR Settings</source>
        <translation>OCR Settings</translation>
    </message>
    <message>
        <source>Log Settings</source>
        <translation>Log Settings</translation>
    </message>
    <message>
        <source>Other</source>
        <translation>Other</translation>
    </message>
    <message>
        <source>About</source>
        <translation>About</translation>
    </message>
    
    <!-- Page Titles -->
    <message>
        <source>Shortcut Settings</source>
        <translation>Shortcut Settings</translation>
    </message>
    <message>
        <source>Screenshot Save Settings</source>
        <translation>Screenshot Save Settings</translation>
    </message>
    <message>
        <source>Other Settings</source>
        <translation>Other Settings</translation>
    </message>
    <message>
        <source>Software Information</source>
        <translation>Software Information</translation>
    </message>
    
    <!-- Buttons -->
    <message>
        <source>Reset This Page</source>
        <translation>Reset This Page</translation>
    </message>
    <message>
        <source>Cancel</source>
        <translation>Cancel</translation>
    </message>
    <message>
        <source>Apply</source>
        <translation>Apply</translation>
    </message>
    <message>
        <source>Change</source>
        <translation>Change</translation>
    </message>
    <message>
        <source>Open</source>
        <translation>Open</translation>
    </message>
    <message>
        <source>Latest Log</source>
        <translation>Latest Log</translation>
    </message>
    
    <!-- Hotkey Page -->
    <message>
        <source>Hotkey</source>
        <translation>Hotkey</translation>
    </message>
    <message>
        <source>e.g.: ctrl+shift+a</source>
        <translation>e.g.: ctrl+shift+a</translation>
    </message>
    <message>
        <source>💡 Hint: You can use modifier keys like Ctrl, Shift, Alt.</source>
        <translation>💡 Hint: You can use modifier keys like Ctrl, Shift, Alt.</translation>
    </message>
    
    <!-- Long Screenshot Page -->
    <message>
        <source>Stitching Engine</source>
        <translation>Stitching Engine</translation>
    </message>
    <message>
        <source>Rust Hash (Recommended)</source>
        <translation>Rust Hash (Recommended)</translation>
    </message>
    <message>
        <source>Python Hash (Debug)</source>
        <translation>Python Hash (Debug)</translation>
    </message>
    <message>
        <source>Wait Time</source>
        <translation>Wait Time</translation>
    </message>
    <message>
        <source>Capture wait time after scroll (seconds)</source>
        <translation>Capture wait time after scroll (seconds)</translation>
    </message>
    
    <!-- Smart Selection Page -->
    <message>
        <source>Enable Smart Selection</source>
        <translation>Enable Smart Selection</translation>
    </message>
    <message>
        <source>Automatically recognizes UI elements at mouse cursor position.</source>
        <translation>Automatically recognizes UI elements at mouse cursor position.</translation>
    </message>
    <message>
        <source>💡 How to use:</source>
        <translation>💡 How to use:</translation>
    </message>
    <message>
        <source>1. Move cursor over window during capture</source>
        <translation>1. Move cursor over window during capture</translation>
    </message>
    <message>
        <source>2. Area will be highlighted with blue border automatically</source>
        <translation>2. Area will be highlighted with blue border automatically</translation>
    </message>
    <message>
        <source>3. Click to select that area</source>
        <translation>3. Click to select that area</translation>
    </message>
    
    <!-- Save Page -->
    <message>
        <source>Auto-save Screenshots</source>
        <translation>Auto-save Screenshots</translation>
    </message>
    <message>
        <source>Automatically saves as file when capturing.</source>
        <translation>Automatically saves as file when capturing.</translation>
    </message>
    <message>
        <source>Save Folder:</source>
        <translation>Save Folder:</translation>
    </message>
    <message>
        <source>💡 Hint: Even with auto-save off, it will be copied to clipboard.</source>
        <translation>💡 Hint: Even with auto-save off, it will be copied to clipboard.</translation>
    </message>
    <message>
        <source>Select Screenshot Save Folder</source>
        <translation>Select Screenshot Save Folder</translation>
    </message>
    
    <!-- OCR Page -->
    <message>
        <source>No OCR Version / OCR module not found</source>
        <translation>No OCR Version / OCR module not found</translation>
    </message>
    <message>
        <source>This is a casual version without OCR.</source>
        <translation>This is a casual version without OCR.</translation>
    </message>
    <message>
        <source>If you need OCR features, please download the full version,</source>
        <translation>If you need OCR features, please download the full version,</translation>
    </message>
    <message>
        <source>or contact the developer:</source>
        <translation>or contact the developer:</translation>
    </message>
    <message>
        <source>Enable OCR</source>
        <translation>Enable OCR</translation>
    </message>
    <message>
        <source>Enables text recognition and selection in pinned windows.</source>
        <translation>Enables text recognition and selection in pinned windows.</translation>
    </message>
    <message>
        <source>Auto language detection: Supports Chinese, Japanese, English mixed recognition</source>
        <translation>Auto language detection: Supports Chinese, Japanese, English mixed recognition</translation>
    </message>
    <message>
        <source>Grayscale Conversion</source>
        <translation>Grayscale Conversion</translation>
    </message>
    <message>
        <source>Image Upscale</source>
        <translation>Image Upscale</translation>
    </message>
    <message>
        <source>Scale:</source>
        <translation>Scale:</translation>
    </message>
    <message>
        <source>💡 If small text cannot be recognized, enable image upscale.</source>
        <translation>💡 If small text cannot be recognized, enable image upscale.</translation>
    </message>
    
    <!-- Log Page -->
    <message>
        <source>Save Logs</source>
        <translation>Save Logs</translation>
    </message>
    <message>
        <source>Saves app activity logs to file.</source>
        <translation>Saves app activity logs to file.</translation>
    </message>
    <message>
        <source>Log Level</source>
        <translation>Log Level</translation>
    </message>
    <message>
        <source>Minimum log level to record</source>
        <translation>Minimum log level to record</translation>
    </message>
    <message>
        <source>Retention Period</source>
        <translation>Retention Period</translation>
    </message>
    <message>
        <source>Auto-delete old logs (0=keep forever)</source>
        <translation>Auto-delete old logs (0=keep forever)</translation>
    </message>
    <message>
        <source>days</source>
        <translation>days</translation>
    </message>
    <message>
        <source>Save Location:</source>
        <translation>Save Location:</translation>
    </message>
    <message>
        <source>Select Log Save Folder</source>
        <translation>Select Log Save Folder</translation>
    </message>
    <message>
        <source>Current Log:</source>
        <translation>Current Log:</translation>
    </message>
    <message>
        <source>Current Log: (Not generated)  *Log will be created after app starts</source>
        <translation>Current Log: (Not generated)  *Log will be created after app starts</translation>
    </message>
    <message>
        <source>Current Log: (Not generated)</source>
        <translation>Current Log: (Not generated)</translation>
    </message>
    <message>
        <source>Log</source>
        <translation>Log</translation>
    </message>
    <message>
        <source>No log files yet. Please start and use the app first.</source>
        <translation>No log files yet. Please start and use the app first.</translation>
    </message>
    <message>
        <source>Log save location changed.</source>
        <translation>Log save location changed.</translation>
    </message>
    <message>
        <source>*Changes will fully take effect after restart.</source>
        <translation>*Changes will fully take effect after restart.</translation>
    </message>
    
    <!-- Misc Page -->
    <message>
        <source>Show Main Window on Startup</source>
        <translation>Show Main Window on Startup</translation>
    </message>
    <message>
        <source>If off, starts in background.</source>
        <translation>If off, starts in background.</translation>
    </message>
    <message>
        <source>Auto-show Drawing Tools on Pin</source>
        <translation>Auto-show Drawing Tools on Pin</translation>
    </message>
    <message>
        <source>On: Shows toolbar when mouse enters pinned window.</source>
        <translation>On: Shows toolbar when mouse enters pinned window.</translation>
    </message>
    <message>
        <source>Off: Show via right-click toolbar button.</source>
        <translation>Off: Show via right-click toolbar button.</translation>
    </message>
    <message>
        <source>🌐 Language / Language</source>
        <translation>🌐 Language</translation>
    </message>
    <message>
        <source>Select display language. Restart required after change.</source>
        <translation>Select display language. Restart required after change.</translation>
    </message>
    <message>
        <source>💡 Hint: Even with background startup, you can operate from system tray.</source>
        <translation>💡 Hint: Even with background startup, you can operate from system tray.</translation>
    </message>
    
    <!-- Info Page -->
    <message>
        <source>Jietuba - Screenshot Tool</source>
        <translation>Jietuba - Screenshot Tool</translation>
    </message>
    <message>
        <source>Version: 1.0.0</source>
        <translation>Version: 1.0.0</translation>
    </message>
    <message>
        <source>High-performance screenshot tool developed based on PyQt6 framework.</source>
        <translation>High-performance screenshot tool developed based on PyQt6 framework.</translation>
    </message>
    <message>
        <source>Rich editing features, OCR text recognition, long screenshot, pin window,</source>
        <translation>Rich editing features, OCR text recognition, long screenshot, pin window,</translation>
    </message>
    <message>
        <source>and many other features.</source>
        <translation>and many other features.</translation>
    </message>
    <message>
        <source>📖 View Details</source>
        <translation>📖 View Details</translation>
    </message>
    <message>
        <source>👨‍💻 Developer: rijyaaru</source>
        <translation>👨‍💻 Developer: rijyaaru</translation>
    </message>
    <message>
        <source>🛠️ Tech: Python + Rust + PyQt6 + PaddleOCR</source>
        <translation>🛠️ Tech: Python + Rust + PyQt6 + PaddleOCR</translation>
    </message>
</context>

<!-- ========== Toolbar ========== -->
<context>
    <name>Toolbar</name>
    <message>
        <source>Long screenshot (scroll)</source>
        <translation>Long screenshot (scroll)</translation>
    </message>
    <message>
        <source>Save to file</source>
        <translation>Save to file</translation>
    </message>
    <message>
        <source>Copy image</source>
        <translation>Copy image</translation>
    </message>
    <message>
        <source>Pen tool (hold Shift for straight line)</source>
        <translation>Pen tool (hold Shift for straight line)</translation>
    </message>
    <message>
        <source>Highlighter (hold Shift for straight line)</source>
        <translation>Highlighter (hold Shift for straight line)</translation>
    </message>
    <message>
        <source>Draw arrow</source>
        <translation>Draw arrow</translation>
    </message>
    <message>
        <source>Number (Shift+scroll to change number)</source>
        <translation>Number (Shift+scroll to change number)</translation>
    </message>
    <message>
        <source>Draw rectangle</source>
        <translation>Draw rectangle</translation>
    </message>
    <message>
        <source>Draw ellipse</source>
        <translation>Draw ellipse</translation>
    </message>
    <message>
        <source>Add text</source>
        <translation>Add text</translation>
    </message>
    <message>
        <source>Eraser tool</source>
        <translation>Eraser tool</translation>
    </message>
    <message>
        <source>Undo</source>
        <translation>Undo</translation>
    </message>
    <message>
        <source>Redo</source>
        <translation>Redo</translation>
    </message>
    <message>
        <source>Screenshot translate (OCR + Translate)</source>
        <translation>Screenshot translate (OCR + Translate)</translation>
    </message>
    <message>
        <source>Recognizing...</source>
        <translation>Recognizing...</translation>
    </message>
    <message>
        <source>Pin image</source>
        <translation>Pin image</translation>
    </message>
    <message>
        <source>Confirm and save</source>
        <translation>Confirm and save</translation>
    </message>
    <message>
        <source>Copy to clipboard</source>
        <translation>Copy to clipboard</translation>
    </message>
    <message>
        <source>Pin to desktop</source>
        <translation>Pin to desktop</translation>
    </message>
    <message>
        <source>Confirm</source>
        <translation>Confirm</translation>
    </message>
    <message>
        <source>Pen</source>
        <translation>Pen</translation>
    </message>
    <message>
        <source>Highlighter</source>
        <translation>Highlighter</translation>
    </message>
    <message>
        <source>Arrow</source>
        <translation>Arrow</translation>
    </message>
    <message>
        <source>Rectangle</source>
        <translation>Rectangle</translation>
    </message>
    <message>
        <source>Ellipse</source>
        <translation>Ellipse</translation>
    </message>
    <message>
        <source>Text</source>
        <translation>Text</translation>
    </message>
    <message>
        <source>Eraser</source>
        <translation>Eraser</translation>
    </message>
    <message>
        <source>Number</source>
        <translation>Number</translation>
    </message>
    <message>
        <source>Long Screenshot</source>
        <translation>Long Screenshot</translation>
    </message>
    <message>
        <source>Record</source>
        <translation>Record</translation>
    </message>
</context>

<!-- ========== Pin Window ========== -->
<context>
    <name>PinWindow</name>
    <message>
        <source>Copy</source>
        <translation>Copy</translation>
    </message>
    <message>
        <source>Save as</source>
        <translation>Save as</translation>
    </message>
    <message>
        <source>Toolbar</source>
        <translation>Toolbar</translation>
    </message>
    <message>
        <source>Always on top</source>
        <translation>Always on top</translation>
    </message>
    <message>
        <source>Shadow effect</source>
        <translation>Shadow effect</translation>
    </message>
    <message>
        <source>Close</source>
        <translation>Close</translation>
    </message>
    <message>
        <source>Close (ESC)</source>
        <translation>Close (ESC)</translation>
    </message>
    <message>
        <source>Show toolbar</source>
        <translation>Show toolbar</translation>
    </message>
    <message>
        <source>Close all pins</source>
        <translation>Close all pins</translation>
    </message>
    <message>
        <source>OCR Recognition</source>
        <translation>OCR Recognition</translation>
    </message>
    <message>
        <source>Reset size</source>
        <translation>Reset size</translation>
    </message>
    <message>
        <source>Translate</source>
        <translation>Translate</translation>
    </message>
    <message>
        <source>Translate OCR text</source>
        <translation>Translate OCR text</translation>
    </message>
</context>

<!-- ========== Scroll Screenshot (Long Screenshot) ========== -->
<context>
    <name>ScrollScreenshotToolbar</name>
    <message>
        <source>Drag to move</source>
        <translation>Drag to move</translation>
    </message>
    <message>
        <source>Vertical</source>
        <translation>Vertical</translation>
    </message>
    <message>
        <source>Horizontal</source>
        <translation>Horizontal</translation>
    </message>
    <message>
        <source>Scroll slowly from top to bottom</source>
        <translation>Scroll slowly from top to bottom</translation>
    </message>
    <message>
        <source>Press Shift or click button</source>
        <translation>Press Shift or click button</translation>
    </message>
    <message>
        <source>Screenshots: 0</source>
        <translation>Screenshots: 0</translation>
    </message>
    <message>
        <source>Screenshots: {count}</source>
        <translation>Screenshots: {count}</translation>
    </message>
    <message>
        <source>Click to take screenshot manually</source>
        <translation>Click to take screenshot manually</translation>
    </message>
    <message>
        <source>Finish</source>
        <translation>Finish</translation>
    </message>
    <message>
        <source>Cancel</source>
        <translation>Cancel</translation>
    </message>
</context>

<!-- ========== System Tray ========== -->
<context>
    <name>SystemTray</name>
    <message>
        <source>jietuba - Double click to open settings</source>
        <translation>jietuba - Double click to open settings</translation>
    </message>
    <message>
        <source>Screenshot</source>
        <translation>Screenshot</translation>
    </message>
    <message>
        <source>Settings</source>
        <translation>Settings</translation>
    </message>
    <message>
        <source>Exit</source>
        <translation>Exit</translation>
    </message>
</context>

<!-- ========== Translation Dialog ========== -->
<context>
    <name>TranslationDialog</name>
    <message>
        <source>Translation Result</source>
        <translation>Translation Result</translation>
    </message>
    <message>
        <source>Original:</source>
        <translation>Original:</translation>
    </message>
    <message>
        <source>Translation:</source>
        <translation>Translation:</translation>
    </message>
    <message>
        <source>Copy Original</source>
        <translation>Copy Original</translation>
    </message>
    <message>
        <source>Copy Translation</source>
        <translation>Copy Translation</translation>
    </message>
    <message>
        <source>Close</source>
        <translation>Close</translation>
    </message>
    <message>
        <source>Translating...</source>
        <translation>Translating...</translation>
    </message>
    <message>
        <source>Translation failed:</source>
        <translation>Translation failed:</translation>
    </message>
    <message>
        <source>Reverse Translate</source>
        <translation>Reverse Translate</translation>
    </message>
    <message>
        <source>Translate the result back to original language</source>
        <translation>Translate the result back to original language</translation>
    </message>
    <message>
        <source>Toggle always on top</source>
        <translation>Toggle always on top</translation>
    </message>
    <message>
        <source>Always on top: ON</source>
        <translation>Always on top: ON</translation>
    </message>
    <message>
        <source>Always on top: OFF</source>
        <translation>Always on top: OFF</translation>
    </message>
    <message>
        <source>Translate text</source>
        <translation>Translate text</translation>
    </message>
    <message>
        <source>Swap languages</source>
        <translation>Swap languages</translation>
    </message>
</context>

<!-- ========== Translation Settings ========== -->
<context>
    <name>SettingsDialog</name>
    <message>
        <source>Translation</source>
        <translation>Translation</translation>
    </message>
    <message>
        <source>Translation Settings</source>
        <translation>Translation Settings</translation>
    </message>
    <message>
        <source>DeepL API Key</source>
        <translation>DeepL API Key</translation>
    </message>
    <message>
        <source>Get your API key from DeepL website (free tier available)</source>
        <translation>Get your API key from DeepL website (free tier available)</translation>
    </message>
    <message>
        <source>Show Key</source>
        <translation>Show Key</translation>
    </message>
    <message>
        <source>Hide Key</source>
        <translation>Hide Key</translation>
    </message>
    <message>
        <source>Use DeepL Pro API</source>
        <translation>Use DeepL Pro API</translation>
    </message>
    <message>
        <source>Enable if you have a paid DeepL subscription</source>
        <translation>Enable if you have a paid DeepL subscription</translation>
    </message>
    <message>
        <source>Target Language</source>
        <translation>Target Language</translation>
    </message>
    <message>
        <source>Leave empty to follow system language</source>
        <translation>Leave empty to follow system language</translation>
    </message>
    <message>
        <source>Auto (System)</source>
        <translation>Auto (System)</translation>
    </message>
    <message>
        <source>Advanced Options</source>
        <translation>Advanced Options</translation>
    </message>
    <message>
        <source>Auto Split Sentences</source>
        <translation>Auto Split Sentences</translation>
    </message>
    <message>
        <source>Automatically split text into sentences for better translation</source>
        <translation>Automatically split text into sentences for better translation</translation>
    </message>
    <message>
        <source>Preserve Formatting</source>
        <translation>Preserve Formatting</translation>
    </message>
    <message>
        <source>Keep original text formatting in translation</source>
        <translation>Keep original text formatting in translation</translation>
    </message>
    <message>
        <source>DeepL free tier: 500,000 chars/month. Get API key at</source>
        <translation>DeepL free tier: 500,000 chars/month. Get API key at</translation>
    </message>
    <message>
        <source>DeepL offers a free API tier with 500,000 characters/month.</source>
        <translation>DeepL offers a free API tier with 500,000 characters/month.</translation>
    </message>
    <message>
        <source>Visit https://www.deepl.com/pro-api to get your API key.</source>
        <translation>Visit https://www.deepl.com/pro-api to get your API key.</translation>
    </message>
</context>

</TS>
